{
    "la cualidad": "the quality",
    "amable": "kind",
    "carin~oso/a": "loving",
    "celoso/a": "jealous",
    "chismoso/a": "gossipy",
    "comprensivo/a": "understanding",
    "considerado/a": "considerate",
    "egoi'sta": "selfish",
    "entrometido/a": "nosy",
    "honesto/a": "honest",
    "i'ntimo/a": "intimate",
    "sincero/a": "sincere",
    "vanidoso/a": "vain",
    "el sustantivo": "the noun",
    "la amistad": "the friendship",
    "la armoni'a": "the harmony",
    "el comportamiento": "the behavior",
    "la confianza": "the trust",
    "el conflicto": "the conflict",
    "la explicacio'n": "the explanation",
    "el malentendido": "the misunderstanding",
    "la pelea": "the fight",
    "el secreto": "the secret",
    "acusar": "to accuse",
    "alegrarse de": "to be happy about",
    "apoyar": "to support",
    "atreverse": "to dare",
    "colaborar": "to collaborate",
    "confiar en": "to trust",
    "contar con": "to count on",
    "criticar": "to criticize",
    "desconfiar": "to mistrust",
    "esperar": "to wait for",
    "estar equivocado/a": "to be mistaken",
    "guardar un secreto": "to keep a secret",
    "ignorar": "to ignore",
    "mejorar": "to improve",
    "pedir perdo'n": "to ask for forgiveness",
    "perdonar": "to forgive",
    "ponerse de acuerdo": "to come to an agreement",
    "reaccionar": "to react",
    "reconciliarse": "to reconcile",
    "reconocer": "to admit",
    "resolver": "to resolve",
    "sorprenderse": "to surprise",
    "temer": "to fear",
    "aceptar tal como ser": "to accept as is",
    "cambiar de opinio'n": "to change opinion",
    "la diferencia de opinio'n": "the difference of opinion",
    "hacer caso": "to pay attention",
    "hacer las paces": "to make peace",
    "juntos/as": "together",
    "ojala'": "I hope",
    "pensar en si' mismo/a": "to think of oneself",
    "que' va": "no way",
    "tener en comu'n": "to have in common",
    "tener celos": "to be jealous",
    "tener la culpa": "to be guilty",
    "yo no fui": "it was not me",
    "enterarse de": "to learn about",
    "encontrarse": "to find oneself",
    "enviar correo": "to send an email",
    "escribir cartas": "to write letters",
    "llevarse bien": "to get along well",
    "quedarse": "to stay",
    "re'irse": "to laugh",
    "bien educado": "well mannered",
    "mal educado": "ill mannered",
    "corte's": "courteous",
    "hasta": "until",
    "infantil": "childish",
    "tonto": "foolish",
    "discrutir": "to argue",
    "gritar": "to shout",
    "llorar": "to cry",
    "mentir": "to lie"
}
